fsd_test_utils/__init__.py
fsd_test_utils/fixtures/__init__.py
fsd_test_utils/fixtures/db_fixtures.py
fsd_test_utils/test_config/__init__.py
fsd_test_utils/test_config/useful_config.py
fsd_utils/__init__.py
fsd_utils/authentication/__init__.py
fsd_utils/authentication/config.py
fsd_utils/authentication/decorators.py
fsd_utils/authentication/models.py
fsd_utils/authentication/utils.py
fsd_utils/config/__init__.py
fsd_utils/config/commonconfig.py
fsd_utils/config/configclass.py
fsd_utils/config/notify_constants.py
fsd_utils/decision/__init__.py
fsd_utils/decision/evaluate_response_against_schema.py
fsd_utils/gunicorn/__init__.py
fsd_utils/gunicorn/config/__init__.py
fsd_utils/gunicorn/config/devtest.py
fsd_utils/gunicorn/config/local.py
fsd_utils/healthchecks/__init__.py
fsd_utils/healthchecks/checkers.py
fsd_utils/healthchecks/healthcheck.py
fsd_utils/locale_selector/__init__.py
fsd_utils/locale_selector/get_lang.py
fsd_utils/locale_selector/set_lang.py
fsd_utils/logging/__init__.py
fsd_utils/logging/logging.py
fsd_utils/mapping/__init__.py
fsd_utils/mapping/application/__init__.py
fsd_utils/mapping/application/application_utils.py
fsd_utils/mapping/application/free_text.py
fsd_utils/mapping/application/languages.py
fsd_utils/mapping/application/multi_input.py
fsd_utils/mapping/application/multi_input_utils.py
fsd_utils/mapping/application/qa_mapping.py
fsd_utils/sentry/__init__.py
fsd_utils/sentry/init_sentry.py
fsd_utils/services/__init__.py
fsd_utils/services/aws.py
fsd_utils/services/aws_extended_client.py
fsd_utils/services/aws_sqs_extended_client_exception.py
fsd_utils/services/aws_sqs_extended_client_util.py
fsd_utils/simple_utils/__init__.py
fsd_utils/simple_utils/data_utils.py
fsd_utils/simple_utils/date_utils.py
fsd_utils/sqs_scheduler/__init__.py
fsd_utils/sqs_scheduler/context_aware_executor.py
fsd_utils/sqs_scheduler/scheduler_service.py
fsd_utils/sqs_scheduler/task_executer_service.py
fsd_utils/toggles/__init__.py
fsd_utils/toggles/toggles.py
funding_service_design_utils-6.1.4.dist-info/licenses/LICENSE
funding_service_design_utils-6.1.4.dist-info/METADATA
funding_service_design_utils-6.1.4.dist-info/WHEEL
funding_service_design_utils-6.1.4.dist-info/top_level.txt
funding_service_design_utils-6.1.4.dist-info/RECORD
