Metadata-Version: 2.4
Name: funding-service-design-utils
Version: 6.1.4
Summary: Utilities used by the MHCLG Funding Service Team
Author-email: MHCLG <FundingService@communities.gov.uk>
License: MIT License
Project-URL: Homepage, https://github.com/communitiesuk/funding-service-design-utils
Classifier: Programming Language :: Python :: 3
Classifier: License :: OSI Approved :: MIT License
Classifier: Operating System :: OS Independent
Requires-Python: <4.0,>=3.10
License-File: LICENSE
Requires-Dist: Flask-Babel>=2.0.0
Requires-Dist: PyYAML>=6.0.1
Requires-Dist: python-dotenv>=1.0.1
Requires-Dist: rich>=12.4.4
Requires-Dist: Flask!=2.3.0,>=2.1.1
Requires-Dist: python-json-logger>=2.0.2
Requires-Dist: gunicorn>=20.1.0
Requires-Dist: pytz>=2022.1
Requires-Dist: PyJWT[crypto]>=2.4.0
Requires-Dist: sentry-sdk[flask]>=2.0.0
Requires-Dist: requests>=2.32.3
Requires-Dist: flask-redis>=0.4.0
Requires-Dist: Flask-Migrate>=4.0.7
Requires-Dist: Flask-SQLAlchemy>=3.0.3
Requires-Dist: sqlalchemy-utils>=0.38.3
Requires-Dist: beautifulsoup4>=4.12.3
Requires-Dist: boto3>=1.9.253
Provides-Extra: toggles
Requires-Dist: flipper-client>=1.3.2; extra == "toggles"
Dynamic: license-file
